dataforge_app.py
dataforge_cli_gui_app-0.1.1.dist-info/licenses/LICENSE.txt
dataforge_cli_gui_app-0.1.1.dist-info/METADATA
dataforge_cli_gui_app-0.1.1.dist-info/WHEEL
dataforge_cli_gui_app-0.1.1.dist-info/entry_points.txt
dataforge_cli_gui_app-0.1.1.dist-info/top_level.txt
dataforge_cli_gui_app-0.1.1.dist-info/RECORD
