Metadata-Version: 2.4
Name: dataforge_cli-gui_app
Version: 0.1.1
Summary: A versatile CLI and GUI tool for converting structured sentences to JSON, YAML, and XML, and querying data files.
Author: Rudra
Author-email: rudra-for-dev@protonmail.com
License: MIT License
Classifier: Programming Language :: Python :: 3
Classifier: Programming Language :: Python :: 3.8
Classifier: Programming Language :: Python :: 3.9
Classifier: Programming Language :: Python :: 3.10
Classifier: Programming Language :: Python :: 3.11
Classifier: License :: OSI Approved :: MIT License
Classifier: Operating System :: OS Independent
Classifier: Topic :: Software Development :: Libraries :: Python Modules
Classifier: Topic :: Utilities
Classifier: Topic :: Text Processing
Classifier: Environment :: X11 Applications :: Qt
License-File: LICENSE.txt
Requires-Dist: PyQt6
Requires-Dist: PyYAML
Dynamic: license-file
